{
  "type": "c4.large",
  "cpus": 2,
  "memory": 3.75,
  "storage": 0,
  "SSD": false,
  "cpuUnits": 2048,
  "memoryUnits": 3840,
  "price": {
    "ap-northeast-1": 0.126,
    "ap-northeast-2": 0.114,
    "ap-south-1": 0.11,
    "ap-southeast-1": 0.115,
    "ap-southeast-2": 0.13,
    "ca-central-1": 0.11,
    "eu-central-1": 0.114,
    "eu-west-1": 0.113,
    "eu-west-2": 0.119,
    "sa-east-1": 0.155,
    "us-east-1": 0.1,
    "us-east-2": 0.1,
    "us-gov-west-1": 0.12,
    "us-west-1": 0.124,
    "us-west-2": 0.1
  },
  "spot": {
    "ap-northeast-1": {
      "overall": {
        "min": 0.0319,
        "max": 1.47,
        "mean": 0.141125,
        "variance": 0.144963,
        "over": 11,
        "count": 145
      },
      "1a": {
        "min": 1.47,
        "max": 1.47,
        "mean": 1.47,
        "variance": 0,
        "over": 11,
        "count": 11
      },
      "1c": {
        "min": 0.0319,
        "max": 0.032,
        "mean": 0.031963,
        "variance": 0,
        "over": 0,
        "count": 38
      },
      "1b": {
        "min": 0.032,
        "max": 0.0322,
        "mean": 0.032068,
        "variance": 0,
        "over": 0,
        "count": 96
      }
    },
    "ap-northeast-2": {
      "overall": {
        "min": 0.0187,
        "max": 1.2,
        "mean": 0.023592,
        "variance": 0.002304,
        "over": 22,
        "count": 3993
      },
      "2c": {
        "min": 0.0187,
        "max": 1.2,
        "mean": 0.025121,
        "variance": 0.003597,
        "over": 22,
        "count": 2547
      },
      "2a": {
        "min": 0.0194,
        "max": 0.0647,
        "mean": 0.020899,
        "variance": 0.000014,
        "over": 0,
        "count": 1446
      }
    },
    "ap-south-1": {
      "overall": {
        "min": 0.0156,
        "max": 1.37,
        "mean": 0.032955,
        "variance": 0.002263,
        "over": 217,
        "count": 19531
      },
      "1a": {
        "min": 0.0156,
        "max": 1.37,
        "mean": 0.033347,
        "variance": 0.003055,
        "over": 108,
        "count": 9628
      },
      "1b": {
        "min": 0.0173,
        "max": 1.37,
        "mean": 0.032575,
        "variance": 0.001491,
        "over": 109,
        "count": 9903
      }
    },
    "ap-southeast-1": {
      "overall": {
        "min": 0.012,
        "max": 0.0171,
        "mean": 0.016147,
        "variance": 0,
        "over": 0,
        "count": 1604
      },
      "1b": {
        "min": 0.012,
        "max": 0.0171,
        "mean": 0.016156,
        "variance": 0,
        "over": 0,
        "count": 1554
      },
      "1a": {
        "min": 0.012,
        "max": 0.016,
        "mean": 0.015862,
        "variance": 0,
        "over": 0,
        "count": 50
      }
    },
    "ap-southeast-2": {
      "overall": {
        "min": 0.0302,
        "max": 0.06,
        "mean": 0.032412,
        "variance": 0.000021,
        "over": 0,
        "count": 2112
      },
      "2b": {
        "min": 0.0303,
        "max": 0.0306,
        "mean": 0.030419,
        "variance": 0,
        "over": 0,
        "count": 360
      },
      "2c": {
        "min": 0.0303,
        "max": 0.06,
        "mean": 0.032888,
        "variance": 0.000025,
        "over": 0,
        "count": 1707
      },
      "2a": {
        "min": 0.0302,
        "max": 0.0305,
        "mean": 0.030309,
        "variance": 0,
        "over": 0,
        "count": 45
      }
    },
    "ca-central-1": {
      "overall": {
        "min": 0.0136,
        "max": 0.022,
        "mean": 0.01633,
        "variance": 0.000001,
        "over": 0,
        "count": 7464
      },
      "1a": {
        "min": 0.0136,
        "max": 0.022,
        "mean": 0.016284,
        "variance": 0.000001,
        "over": 0,
        "count": 5117
      },
      "1b": {
        "min": 0.0146,
        "max": 0.019,
        "mean": 0.016432,
        "variance": 0.000001,
        "over": 0,
        "count": 2347
      }
    },
    "eu-central-1": {
      "overall": {
        "min": 0.0173,
        "max": 0.15,
        "mean": 0.030347,
        "variance": 0.000291,
        "over": 39,
        "count": 9471
      },
      "1c": {
        "min": 0.0174,
        "max": 0.15,
        "mean": 0.033398,
        "variance": 0.00032,
        "over": 39,
        "count": 7544
      },
      "1b": {
        "min": 0.0173,
        "max": 0.0213,
        "mean": 0.01846,
        "variance": 0,
        "over": 0,
        "count": 925
      },
      "1a": {
        "min": 0.0175,
        "max": 0.0192,
        "mean": 0.018349,
        "variance": 0,
        "over": 0,
        "count": 1002
      }
    },
    "eu-west-1": {
      "overall": {
        "min": 0.0289,
        "max": 0.0294,
        "mean": 0.029024,
        "variance": 0,
        "over": 0,
        "count": 448
      },
      "1b": {
        "min": 0.0289,
        "max": 0.0294,
        "mean": 0.029069,
        "variance": 0,
        "over": 0,
        "count": 140
      },
      "1a": {
        "min": 0.0289,
        "max": 0.0292,
        "mean": 0.029015,
        "variance": 0,
        "over": 0,
        "count": 221
      },
      "1c": {
        "min": 0.0289,
        "max": 0.0291,
        "mean": 0.028976,
        "variance": 0,
        "over": 0,
        "count": 87
      }
    },
    "eu-west-2": {
      "overall": {
        "min": 0.0125,
        "max": 1.19,
        "mean": 0.040373,
        "variance": 0.013193,
        "over": 481,
        "count": 20184
      },
      "2b": {
        "min": 0.0128,
        "max": 1.19,
        "mean": 0.044213,
        "variance": 0.014503,
        "over": 310,
        "count": 10128
      },
      "2a": {
        "min": 0.0125,
        "max": 1.19,
        "mean": 0.036505,
        "variance": 0.011843,
        "over": 171,
        "count": 10056
      }
    },
    "sa-east-1": {
      "overall": {
        "min": 0.0172,
        "max": 1.63,
        "mean": 0.0297,
        "variance": 0.008626,
        "over": 39,
        "count": 9898
      },
      "1c": {
        "min": 0.0176,
        "max": 1.63,
        "mean": 0.031664,
        "variance": 0.010959,
        "over": 27,
        "count": 4941
      },
      "1a": {
        "min": 0.0172,
        "max": 1.63,
        "mean": 0.024504,
        "variance": 0.001105,
        "over": 2,
        "count": 4947
      },
      "1b": {
        "min": 1.63,
        "max": 1.63,
        "mean": 1.63,
        "variance": 0,
        "over": 10,
        "count": 10
      }
    },
    "us-east-1": {
      "overall": {
        "min": null,
        "max": null,
        "mean": null,
        "variance": null,
        "over": null,
        "count": 0
      }
    },
    "us-east-2": {
      "overall": {
        "min": 0.0107,
        "max": 0.0201,
        "mean": 0.015606,
        "variance": 0.000003,
        "over": 0,
        "count": 6695
      },
      "2c": {
        "min": 0.0119,
        "max": 0.02,
        "mean": 0.016306,
        "variance": 0.000003,
        "over": 0,
        "count": 2966
      },
      "2b": {
        "min": 0.0115,
        "max": 0.0201,
        "mean": 0.015397,
        "variance": 0.000005,
        "over": 0,
        "count": 1585
      },
      "2a": {
        "min": 0.0107,
        "max": 0.0201,
        "mean": 0.014791,
        "variance": 0.000002,
        "over": 0,
        "count": 2144
      }
    },
    "us-west-1": {
      "overall": {
        "min": 0.0174,
        "max": 0.0184,
        "mean": 0.017959,
        "variance": 0,
        "over": 0,
        "count": 389
      },
      "1b": {
        "min": 0.0177,
        "max": 0.018,
        "mean": 0.017795,
        "variance": 0,
        "over": 0,
        "count": 118
      },
      "1c": {
        "min": 0.0176,
        "max": 0.0184,
        "mean": 0.018063,
        "variance": 0,
        "over": 0,
        "count": 258
      },
      "1a": {
        "min": 0.0174,
        "max": 0.0174,
        "mean": 0.0174,
        "variance": 0,
        "over": 0,
        "count": 13
      }
    },
    "us-west-2": {
      "overall": {
        "min": 0.0219,
        "max": 0.0227,
        "mean": 0.022127,
        "variance": 0,
        "over": 0,
        "count": 406
      },
      "2a": {
        "min": 0.0219,
        "max": 0.022,
        "mean": 0.021945,
        "variance": 0,
        "over": 0,
        "count": 110
      },
      "2c": {
        "min": 0.022,
        "max": 0.0227,
        "mean": 0.022301,
        "variance": 0,
        "over": 0,
        "count": 171
      },
      "2b": {
        "min": 0.022,
        "max": 0.0221,
        "mean": 0.022049,
        "variance": 0,
        "over": 0,
        "count": 125
      }
    }
  }
}