{
  "type": "m4.10xlarge",
  "cpus": 40,
  "memory": 160,
  "storage": 0,
  "SSD": false,
  "cpuUnits": 40960,
  "memoryUnits": 163840,
  "price": {
    "ap-northeast-1": 2.58,
    "ap-northeast-2": 2.46,
    "ap-south-1": 2.46,
    "ap-southeast-1": 2.5,
    "ap-southeast-2": 2.5,
    "ca-central-1": 2.22,
    "eu-central-1": 2.4,
    "eu-west-1": 2.22,
    "eu-west-2": 2.32,
    "sa-east-1": 3.18,
    "us-east-1": 2,
    "us-east-2": 2,
    "us-gov-west-1": 2.52,
    "us-west-1": 2.34,
    "us-west-2": 2
  },
  "spot": {
    "ap-northeast-1": {
      "overall": {
        "min": 0.6218,
        "max": 2.58,
        "mean": 1.11135,
        "variance": 0.718978,
        "over": 6,
        "count": 24
      },
      "1b": {
        "min": 0.6218,
        "max": 0.6218,
        "mean": 0.6218,
        "variance": 0,
        "over": 0,
        "count": 9
      },
      "1a": {
        "min": 2.58,
        "max": 2.58,
        "mean": 2.58,
        "variance": 0,
        "over": 6,
        "count": 6
      },
      "1c": {
        "min": 0.6218,
        "max": 0.6218,
        "mean": 0.6218,
        "variance": 0,
        "over": 0,
        "count": 9
      }
    },
    "ap-northeast-2": {
      "overall": {
        "min": 0.5601,
        "max": 1.996448,
        "mean": 0.942392,
        "variance": 0.374085,
        "over": 0,
        "count": 255
      },
      "2c": {
        "min": 1.7031,
        "max": 1.996448,
        "mean": 1.914025,
        "variance": 0.009378,
        "over": 0,
        "count": 72
      },
      "2a": {
        "min": 0.5601,
        "max": 0.560123,
        "mean": 0.560111,
        "variance": 0,
        "over": 0,
        "count": 183
      }
    },
    "ap-south-1": {
      "overall": {
        "min": 0.4248,
        "max": 0.5,
        "mean": 0.440976,
        "variance": 0.000205,
        "over": 0,
        "count": 330
      },
      "1a": {
        "min": 0.4248,
        "max": 0.4929,
        "mean": 0.4542,
        "variance": 0.00042,
        "over": 0,
        "count": 39
      },
      "1b": {
        "min": 0.42896,
        "max": 0.5,
        "mean": 0.439204,
        "variance": 0.000149,
        "over": 0,
        "count": 291
      }
    },
    "ap-southeast-1": {
      "overall": {
        "min": 0.5605,
        "max": 0.6066,
        "mean": 0.589176,
        "variance": 0.000165,
        "over": 0,
        "count": 41
      },
      "1a": {
        "min": 0.5605,
        "max": 0.6066,
        "mean": 0.591166,
        "variance": 0.000193,
        "over": 0,
        "count": 32
      },
      "1b": {
        "min": 0.5821,
        "max": 0.5821,
        "mean": 0.5821,
        "variance": 0,
        "over": 0,
        "count": 9
      }
    },
    "ap-southeast-2": {
      "overall": {
        "min": 0.527,
        "max": 0.644,
        "mean": 0.543042,
        "variance": 0.000613,
        "over": 0,
        "count": 429
      },
      "2b": {
        "min": 0.5457,
        "max": 0.644,
        "mean": 0.595389,
        "variance": 0.000834,
        "over": 0,
        "count": 36
      },
      "2a": {
        "min": 0.527,
        "max": 0.613,
        "mean": 0.569131,
        "variance": 0.000588,
        "over": 0,
        "count": 35
      },
      "2c": {
        "min": 0.5283,
        "max": 0.6171,
        "mean": 0.535228,
        "variance": 0.00019,
        "over": 0,
        "count": 358
      }
    },
    "ca-central-1": {
      "overall": {
        "min": 0.3435,
        "max": 0.4213,
        "mean": 0.362662,
        "variance": 0.000142,
        "over": 0,
        "count": 790
      },
      "1a": {
        "min": 0.3584,
        "max": 0.4213,
        "mean": 0.367006,
        "variance": 0.000064,
        "over": 0,
        "count": 586
      },
      "1b": {
        "min": 0.3435,
        "max": 0.4009,
        "mean": 0.350184,
        "variance": 0.000156,
        "over": 0,
        "count": 204
      }
    },
    "eu-central-1": {
      "overall": {
        "min": 0.8419,
        "max": 1.917,
        "mean": 1.205356,
        "variance": 0.162056,
        "over": 0,
        "count": 108
      },
      "1c": {
        "min": 0.9134,
        "max": 0.9768,
        "mean": 0.941468,
        "variance": 0.000417,
        "over": 0,
        "count": 37
      },
      "1b": {
        "min": 0.8419,
        "max": 0.9943,
        "mean": 0.916606,
        "variance": 0.001949,
        "over": 0,
        "count": 36
      },
      "1a": {
        "min": 1.6477,
        "max": 1.917,
        "mean": 1.781326,
        "variance": 0.006495,
        "over": 0,
        "count": 35
      }
    },
    "eu-west-1": {
      "overall": {
        "min": 0.6421,
        "max": 0.6758,
        "mean": 0.653931,
        "variance": 0.000155,
        "over": 0,
        "count": 52
      },
      "1b": {
        "min": 0.6421,
        "max": 0.6516,
        "mean": 0.643345,
        "variance": 0.000008,
        "over": 0,
        "count": 11
      },
      "1c": {
        "min": 0.6421,
        "max": 0.6758,
        "mean": 0.660897,
        "variance": 0.000123,
        "over": 0,
        "count": 32
      },
      "1a": {
        "min": 0.6421,
        "max": 0.6421,
        "mean": 0.6421,
        "variance": 0,
        "over": 0,
        "count": 9
      }
    },
    "eu-west-2": {
      "overall": {
        "min": 0.3454,
        "max": 0.5873,
        "mean": 0.473819,
        "variance": 0.013569,
        "over": 0,
        "count": 677
      },
      "2b": {
        "min": 0.3454,
        "max": 0.3984,
        "mean": 0.35451,
        "variance": 0.000066,
        "over": 0,
        "count": 330
      },
      "2a": {
        "min": 0.587265,
        "max": 0.5873,
        "mean": 0.587283,
        "variance": 0,
        "over": 0,
        "count": 347
      }
    },
    "sa-east-1": {
      "overall": {
        "min": 2.3536,
        "max": 2.7714,
        "mean": 2.59069,
        "variance": 0.012964,
        "over": 0,
        "count": 80
      },
      "1a": {
        "min": 2.3536,
        "max": 2.7556,
        "mean": 2.597088,
        "variance": 0.011435,
        "over": 0,
        "count": 45
      },
      "1c": {
        "min": 2.3572,
        "max": 2.7714,
        "mean": 2.582465,
        "variance": 0.01481,
        "over": 0,
        "count": 35
      }
    },
    "us-east-1": {
      "overall": {
        "min": null,
        "max": null,
        "mean": null,
        "variance": null,
        "over": null,
        "count": 0
      }
    },
    "us-east-2": {
      "overall": {
        "min": 0.3552,
        "max": 0.3618,
        "mean": 0.355252,
        "variance": 0,
        "over": 0,
        "count": 969
      },
      "2c": {
        "min": 0.3552,
        "max": 0.355215,
        "mean": 0.355207,
        "variance": 0,
        "over": 0,
        "count": 176
      },
      "2b": {
        "min": 0.3552,
        "max": 0.355215,
        "mean": 0.355207,
        "variance": 0,
        "over": 0,
        "count": 212
      },
      "2a": {
        "min": 0.3552,
        "max": 0.3618,
        "mean": 0.355283,
        "variance": 0,
        "over": 0,
        "count": 581
      }
    },
    "us-west-1": {
      "overall": {
        "min": 0.7922,
        "max": 1.0647,
        "mean": 0.982032,
        "variance": 0.004706,
        "over": 0,
        "count": 484
      },
      "1c": {
        "min": 0.987,
        "max": 1.0647,
        "mean": 1.011546,
        "variance": 0.000078,
        "over": 0,
        "count": 407
      },
      "1b": {
        "min": 0.7922,
        "max": 0.8516,
        "mean": 0.826029,
        "variance": 0.000224,
        "over": 0,
        "count": 77
      }
    },
    "us-west-2": {
      "overall": {
        "min": 0.6018,
        "max": 0.633,
        "mean": 0.610529,
        "variance": 0.000105,
        "over": 0,
        "count": 56
      },
      "2c": {
        "min": 0.6018,
        "max": 0.6018,
        "mean": 0.6018,
        "variance": 0,
        "over": 0,
        "count": 11
      },
      "2b": {
        "min": 0.605,
        "max": 0.633,
        "mean": 0.616176,
        "variance": 0.000092,
        "over": 0,
        "count": 34
      },
      "2a": {
        "min": 0.6018,
        "max": 0.6018,
        "mean": 0.6018,
        "variance": 0,
        "over": 0,
        "count": 11
      }
    }
  }
}