{
  "type": "t2.large",
  "cpus": 2,
  "memory": 8,
  "storage": 0,
  "SSD": false,
  "cpuUnits": 2048,
  "memoryUnits": 8192,
  "price": {
    "ap-northeast-1": 0.1216,
    "ap-northeast-2": 0.1152,
    "ap-south-1": 0.1152,
    "ap-southeast-1": 0.1168,
    "ap-southeast-2": 0.1168,
    "ca-central-1": 0.1024,
    "eu-central-1": 0.1072,
    "eu-west-1": 0.1008,
    "eu-west-2": 0.1056,
    "sa-east-1": 0.1488,
    "us-east-1": 0.0928,
    "us-east-2": 0.0928,
    "us-gov-west-1": 0.1088,
    "us-west-1": 0.1104,
    "us-west-2": 0.0928
  },
  "spot": {
    "ap-northeast-1": {
      "overall": {
        "min": 0.0405,
        "max": 0.089,
        "mean": 0.057066,
        "variance": 0.000312,
        "over": 0,
        "count": 93
      },
      "1b": {
        "min": 0.0405,
        "max": 0.0477,
        "mean": 0.044213,
        "variance": 0.000005,
        "over": 0,
        "count": 31
      },
      "1a": {
        "min": 0.0756,
        "max": 0.089,
        "mean": 0.081719,
        "variance": 0.000016,
        "over": 0,
        "count": 31
      },
      "1c": {
        "min": 0.0415,
        "max": 0.0486,
        "mean": 0.045265,
        "variance": 0.000004,
        "over": 0,
        "count": 31
      }
    },
    "ap-northeast-2": {
      "overall": {
        "min": 0.0389,
        "max": 0.0456,
        "mean": 0.044066,
        "variance": 0.000001,
        "over": 0,
        "count": 639
      },
      "2a": {
        "min": 0.0389,
        "max": 0.0456,
        "mean": 0.044714,
        "variance": 0.000002,
        "over": 0,
        "count": 181
      },
      "2c": {
        "min": 0.039,
        "max": 0.0455,
        "mean": 0.04381,
        "variance": 0,
        "over": 0,
        "count": 458
      }
    },
    "ap-south-1": {
      "overall": {
        "min": 0.0387,
        "max": 0.0457,
        "mean": 0.043965,
        "variance": 0.000002,
        "over": 0,
        "count": 341
      },
      "1a": {
        "min": 0.0387,
        "max": 0.0456,
        "mean": 0.044118,
        "variance": 0.000001,
        "over": 0,
        "count": 303
      },
      "1b": {
        "min": 0.0391,
        "max": 0.0457,
        "mean": 0.042747,
        "variance": 0.000004,
        "over": 0,
        "count": 38
      }
    },
    "ap-southeast-1": {
      "overall": {
        "min": 0.0392,
        "max": 0.0463,
        "mean": 0.042731,
        "variance": 0.000004,
        "over": 0,
        "count": 67
      },
      "1b": {
        "min": 0.0392,
        "max": 0.0462,
        "mean": 0.042612,
        "variance": 0.000005,
        "over": 0,
        "count": 34
      },
      "1a": {
        "min": 0.0398,
        "max": 0.0463,
        "mean": 0.042855,
        "variance": 0.000004,
        "over": 0,
        "count": 33
      }
    },
    "ap-southeast-2": {
      "overall": {
        "min": 0.039,
        "max": 0.0465,
        "mean": 0.045051,
        "variance": 0.000002,
        "over": 0,
        "count": 773
      },
      "2b": {
        "min": 0.039,
        "max": 0.0455,
        "mean": 0.042225,
        "variance": 0.000003,
        "over": 0,
        "count": 32
      },
      "2c": {
        "min": 0.0399,
        "max": 0.0465,
        "mean": 0.045185,
        "variance": 0.000001,
        "over": 0,
        "count": 476
      },
      "2a": {
        "min": 0.0396,
        "max": 0.0465,
        "mean": 0.045151,
        "variance": 0.000002,
        "over": 0,
        "count": 265
      }
    },
    "ca-central-1": {
      "overall": {
        "min": 0.0347,
        "max": 0.0408,
        "mean": 0.039814,
        "variance": 0.000001,
        "over": 0,
        "count": 628
      },
      "1b": {
        "min": 0.0347,
        "max": 0.0408,
        "mean": 0.039898,
        "variance": 0.000001,
        "over": 0,
        "count": 420
      },
      "1a": {
        "min": 0.0349,
        "max": 0.0406,
        "mean": 0.039645,
        "variance": 0.000001,
        "over": 0,
        "count": 208
      }
    },
    "eu-central-1": {
      "overall": {
        "min": 0.036,
        "max": 0.0426,
        "mean": 0.039299,
        "variance": 0.000004,
        "over": 0,
        "count": 112
      },
      "1b": {
        "min": 0.0361,
        "max": 0.0425,
        "mean": 0.039392,
        "variance": 0.000004,
        "over": 0,
        "count": 37
      },
      "1a": {
        "min": 0.036,
        "max": 0.0424,
        "mean": 0.039157,
        "variance": 0.000004,
        "over": 0,
        "count": 37
      },
      "1c": {
        "min": 0.0365,
        "max": 0.0426,
        "mean": 0.039347,
        "variance": 0.000003,
        "over": 0,
        "count": 38
      }
    },
    "eu-west-1": {
      "overall": {
        "min": 0.0344,
        "max": 0.0406,
        "mean": 0.037498,
        "variance": 0.000003,
        "over": 0,
        "count": 86
      },
      "1a": {
        "min": 0.0344,
        "max": 0.0406,
        "mean": 0.0373,
        "variance": 0.000003,
        "over": 0,
        "count": 29
      },
      "1c": {
        "min": 0.0351,
        "max": 0.0406,
        "mean": 0.037661,
        "variance": 0.000003,
        "over": 0,
        "count": 28
      },
      "1b": {
        "min": 0.035,
        "max": 0.0405,
        "mean": 0.037538,
        "variance": 0.000003,
        "over": 0,
        "count": 29
      }
    },
    "eu-west-2": {
      "overall": {
        "min": 0.0358,
        "max": 0.0418,
        "mean": 0.040948,
        "variance": 0.000001,
        "over": 0,
        "count": 542
      },
      "2a": {
        "min": 0.0358,
        "max": 0.0418,
        "mean": 0.04103,
        "variance": 0.000002,
        "over": 0,
        "count": 168
      },
      "2b": {
        "min": 0.0359,
        "max": 0.0417,
        "mean": 0.040911,
        "variance": 0.000001,
        "over": 0,
        "count": 374
      }
    },
    "sa-east-1": {
      "overall": {
        "min": 0.0506,
        "max": 0.0596,
        "mean": 0.056839,
        "variance": 0.000005,
        "over": 0,
        "count": 225
      },
      "1a": {
        "min": 0.051,
        "max": 0.0596,
        "mean": 0.055276,
        "variance": 0.000007,
        "over": 0,
        "count": 29
      },
      "1c": {
        "min": 0.0508,
        "max": 0.0594,
        "mean": 0.057041,
        "variance": 0.000007,
        "over": 0,
        "count": 58
      },
      "1b": {
        "min": 0.0506,
        "max": 0.0592,
        "mean": 0.057082,
        "variance": 0.000002,
        "over": 0,
        "count": 138
      }
    },
    "us-east-1": {
      "overall": {
        "min": null,
        "max": null,
        "mean": null,
        "variance": null,
        "over": null,
        "count": 0
      }
    },
    "us-east-2": {
      "overall": {
        "min": 0.0311,
        "max": 0.037,
        "mean": 0.035906,
        "variance": 0.000001,
        "over": 0,
        "count": 1076
      },
      "2a": {
        "min": 0.0311,
        "max": 0.0364,
        "mean": 0.035433,
        "variance": 0.000001,
        "over": 0,
        "count": 312
      },
      "2b": {
        "min": 0.0315,
        "max": 0.036946,
        "mean": 0.036263,
        "variance": 0.000001,
        "over": 0,
        "count": 574
      },
      "2c": {
        "min": 0.0318,
        "max": 0.037,
        "mean": 0.035605,
        "variance": 0.000001,
        "over": 0,
        "count": 190
      }
    },
    "us-west-1": {
      "overall": {
        "min": 0.0373,
        "max": 0.0437,
        "mean": 0.042083,
        "variance": 0.000002,
        "over": 0,
        "count": 310
      },
      "1c": {
        "min": 0.0375,
        "max": 0.0436,
        "mean": 0.040633,
        "variance": 0.000003,
        "over": 0,
        "count": 36
      },
      "1b": {
        "min": 0.0373,
        "max": 0.0437,
        "mean": 0.042274,
        "variance": 0.000001,
        "over": 0,
        "count": 274
      }
    },
    "us-west-2": {
      "overall": {
        "min": 0.0315,
        "max": 0.0373,
        "mean": 0.03429,
        "variance": 0.000003,
        "over": 0,
        "count": 88
      },
      "2a": {
        "min": 0.0317,
        "max": 0.0369,
        "mean": 0.034176,
        "variance": 0.000002,
        "over": 0,
        "count": 29
      },
      "2c": {
        "min": 0.0318,
        "max": 0.0372,
        "mean": 0.03433,
        "variance": 0.000003,
        "over": 0,
        "count": 30
      },
      "2b": {
        "min": 0.0315,
        "max": 0.0373,
        "mean": 0.034362,
        "variance": 0.000003,
        "over": 0,
        "count": 29
      }
    }
  }
}